LICENSE
MANIFEST.in
README.md
setup.py
redo/__init__.py
redo/atoi.py
redo/builder.py
redo/cmd_always.py
redo/cmd_ifchange.py
redo/cmd_ifcreate.py
redo/cmd_log.py
redo/cmd_ood.py
redo/cmd_redo.py
redo/cmd_sources.py
redo/cmd_stamp.py
redo/cmd_targets.py
redo/cmd_unlocked.py
redo/cmd_whichdo.py
redo/cycles.py
redo/deps.py
redo/env.py
redo/helpers.py
redo/jobserver.py
redo/logs.py
redo/options.py
redo/paths.py
redo/state.py
redo/title.py
redo/version/__init__.py
redo/version/_version.py
redo_tools.egg-info/PKG-INFO
redo_tools.egg-info/SOURCES.txt
redo_tools.egg-info/dependency_links.txt
redo_tools.egg-info/entry_points.txt
redo_tools.egg-info/top_level.txt