Metadata-Version: 1.2
Name: redo-tools
Version: 0.41
Summary: djb redo: a recursive, general purpose build system.
Home-page: https://github.com/apenwarr/redo
Author: Avery Pennarun
Author-email: apenwarr@gmail.com
License: Apache
Keywords: redo redo-ifchange make dependencies build system compiler
Platform: UNKNOWN
Classifier: Development Status :: 4 - Beta
Classifier: Environment :: Console
Classifier: Topic :: Utilities
Classifier: License :: OSI Approved :: Apache Software License
Classifier: Operating System :: POSIX
Classifier: Topic :: Software Development :: Build Tools
Classifier: Topic :: Utilities
Requires-Python: >=2.7, <3.0
